folder2prompt_cli/__init__.py
folder2prompt_cli/main.py
folder2prompt_cli-0.1.2.dist-info/LICENSE
folder2prompt_cli-0.1.2.dist-info/METADATA
folder2prompt_cli-0.1.2.dist-info/WHEEL
folder2prompt_cli-0.1.2.dist-info/entry_points.txt
folder2prompt_cli-0.1.2.dist-info/top_level.txt
folder2prompt_cli-0.1.2.dist-info/RECORD
