Metadata-Version: 2.1
Name: folder2prompt-cli
Version: 0.1.2
Summary: A CLI tool to convert files in a directory to a text output.
Author-email: James Kim <hashd2035@gmail.com>
Project-URL: Homepage, https://github.com/hashd2035/folder2prompt
Project-URL: Bug Tracker, https://github.com/hashd2035/folder2prompt/issues
Classifier: Programming Language :: Python :: 3
Classifier: License :: OSI Approved :: MIT License
Classifier: Operating System :: OS Independent
Requires-Python: >=3.7
License-File: LICENSE
